[
    {
      "image": "images/CodeQuiz Img.png",
      "title": "JavaScript Quiz",
      "description": "This project is designed to test one's knowledge of JavaScript in a multiple choice test format, utilizing html, css, and javascript",
      "link": "https://github.com/avilwock/Code-Quiz",
      "projectLink": "https://avilwock.github.io/Code-Quiz/",
      "isSpecial": false
    },
    {
      "image": "images/JATE.png",
      "title": "Text Editor",
      "description": "This project is designed to store data online and offline",
      "link": "https://github.com/avilwock/Text-Editor",
      "projectLink": "https://text-editor-pou8.onrender.com",
      "isSpecial": false
    },
    {
      "image": "images/TechBlog.png",
      "title": "Tech Blog",
      "description": "a blog to talk about fun tech related facts",
      "link": "https://github.com/avilwock/Tech-Blog",
      "projectLink": "https://warm-sands-36519-225dbeb270ac.herokuapp.com/",
      "isSpecial": false
    },
    {
      "image": "images/WorkDayScheduler.png",
      "title": "Work Day Scheduler",
      "description": "A place to fill out everything you need to accomplish during your workday",
      "link": "https://github.com/avilwock/Work-Day-Scheduler",
      "projectLink": "https://avilwock.github.io/Work-Day-Scheduler/",
      "isSpecial": false
    },
    {
      "image": "images/READMEGenerator.png",
      "title": "README Generator",
      "description": "a series of prompts that you can answer to easily generate your own README",
      "link": "https://github.com/avilwock/README-Generator",
      "isSpecial": false
    },
    {
      "image": "images/PageTurnerPlates.png",
      "title": "Page Turner Plates",
      "description": "an app used to find recipes, and books related to the ingredient searched",
      "link": "https://github.com/avilwock/Page-Turner-Plates",
      "projectLink": "https://avilwock.github.io/Page-Turner-Plates/",
      "isSpecial": false
    },
    {
      "image": "images/Car-GO.png",
      "title": "Car-GO",
      "description": "a blog used to discuss issues related to cars",
      "link": "https://github.com/avilwock/Car-GO",
      "projectLink": "https://warm-headland-43159-c6c90b718fb4.herokuapp.com/",
      "isSpecial": false
    },
    {
      "image": "images/Galaxy.jpg",
      "title": "Goal Galaxy",
      "comingSoon": "Coming Soon",
      "description": "a goal planning activity tracker app",
      "link": "https://github.com/avilwock/Goal-Galaxy",
      "isSpecial": false,
      "isComingSoon": true
    }
  ]
  